bws_scheduler/__init__.py
bws_scheduler/scheduler.py
bws_scheduler/task.py
bws_scheduler/utils.py
bws_scheduler-0.0.1.dist-info/LICENSE
bws_scheduler-0.0.1.dist-info/WHEEL
bws_scheduler-0.0.1.dist-info/METADATA
bws_scheduler-0.0.1.dist-info/RECORD
